gdash/__init__.py
gdash/__main__.py
gdash/version.py
gdash/ui/asset-manifest.json
gdash/ui/index.html
gdash/ui/logo-small.png
gdash/ui/logo.png
gdash/ui/manifest.json
gdash/ui/robots.txt
gdash/ui/static/css/main.bb354ed4.css
gdash/ui/static/css/main.bb354ed4.css.map
gdash/ui/static/js/main.c4611ae3.js
gdash/ui/static/js/main.c4611ae3.js.LICENSE.txt
gdash/ui/static/js/main.c4611ae3.js.map
gdash/ui/static/media/bg1.434ec9b5178c983b027e73e271858301.svg
gdash-1.1.7.dist-info/LICENSE
gdash-1.1.7.dist-info/METADATA
gdash-1.1.7.dist-info/WHEEL
gdash-1.1.7.dist-info/entry_points.txt
gdash-1.1.7.dist-info/top_level.txt
gdash-1.1.7.dist-info/RECORD
